{
    "openapi": "3.0.0",
    "info": {
        "title": "Luizalabs - Conta Corrente",
        "description": "Documentation for the Application API",
        "version": "1.0.0"
    },
    "servers": [
        {
            "url": "http://127.0.0.1:9000/api",
            "description": "Luizalabs - Conta Corrente Server #1"
        }
    ],
    "paths": {
        "/v1/login": {
            "post": {
                "summary": "Autentica um Usu\u00e1rio.",
                "description": "",
                "deprecated": false,
                "responses": {
                    "200": {
                        "description": "OK"
                    },
                    "401": {
                        "description": "(Unauthorized) Invalid or missing Access Token"
                    }
                },
                "tags": [
                    "Autentica\u00e7\u00e3o"
                ]
            }
        },
        "/v1/register": {
            "post": {
                "summary": "Cria um novo Usu\u00e1rio.",
                "description": "",
                "deprecated": false,
                "responses": {
                    "200": {
                        "description": "OK"
                    },
                    "401": {
                        "description": "(Unauthorized) Invalid or missing Access Token"
                    }
                },
                "tags": [
                    "Autentica\u00e7\u00e3o"
                ]
            }
        },
        "/v1/user": {
            "post": {
                "summary": "Exibe os dados do Usu\u00e1rio autenticado.",
                "description": "",
                "deprecated": false,
                "responses": {
                    "200": {
                        "description": "OK"
                    },
                    "401": {
                        "description": "(Unauthorized) Invalid or missing Access Token"
                    }
                },
                "tags": [
                    "Autentica\u00e7\u00e3o"
                ],
                "security": [
                    {
                        "bearerAuth": []
                    }
                ]
            }
        },
        "/v1/logout": {
            "post": {
                "summary": "Desautentica um Usu\u00e1rio.",
                "description": "",
                "deprecated": false,
                "responses": {
                    "200": {
                        "description": "OK"
                    },
                    "401": {
                        "description": "(Unauthorized) Invalid or missing Access Token"
                    }
                },
                "tags": [
                    "Autentica\u00e7\u00e3o"
                ],
                "security": [
                    {
                        "bearerAuth": []
                    }
                ]
            }
        },
        "/v1/transactions": {
            "get": {
                "summary": "Recupera uma lista paginada de transa\u00e7\u00f5es do usu\u00e1rio.",
                "description": "",
                "deprecated": false,
                "responses": {
                    "200": {
                        "description": "OK"
                    },
                    "401": {
                        "description": "(Unauthorized) Invalid or missing Access Token"
                    }
                },
                "tags": [
                    "Transa\u00e7\u00e3o"
                ],
                "security": [
                    {
                        "bearerAuth": []
                    }
                ]
            },
            "post": {
                "summary": "Cria uma nova transa\u00e7\u00e3o.",
                "description": "",
                "deprecated": false,
                "responses": {
                    "200": {
                        "description": "OK"
                    },
                    "401": {
                        "description": "(Unauthorized) Invalid or missing Access Token"
                    }
                },
                "tags": [
                    "Transa\u00e7\u00e3o"
                ],
                "requestBody": {
                    "content": {
                        "application/json": {
                            "schema": {
                                "required": [
                                    "type",
                                    "amount",
                                    "account_number"
                                ],
                                "properties": {
                                    "description": {
                                        "type": "string",
                                        "nullable": true
                                    },
                                    "type": {
                                        "type": "string",
                                        "maxLength": 255
                                    },
                                    "amount": {
                                        "type": "string",
                                        "minLength": 0
                                    },
                                    "account_number": {
                                        "type": "integer"
                                    },
                                    "payee_number": {
                                        "type": "integer",
                                        "nullable": true
                                    }
                                }
                            }
                        }
                    }
                },
                "security": [
                    {
                        "bearerAuth": []
                    }
                ]
            }
        },
        "/v1/transactions/{transaction}": {
            "get": {
                "summary": "Recupera os dados de uma transa\u00e7\u00e3o espec\u00edfica.",
                "description": "",
                "deprecated": false,
                "responses": {
                    "200": {
                        "description": "OK"
                    },
                    "401": {
                        "description": "(Unauthorized) Invalid or missing Access Token"
                    }
                },
                "tags": [
                    "Transa\u00e7\u00e3o"
                ],
                "parameters": [
                    {
                        "name": "transaction",
                        "in": "path",
                        "required": true,
                        "description": "",
                        "schema": {
                            "type": "string"
                        }
                    }
                ],
                "security": [
                    {
                        "bearerAuth": []
                    }
                ]
            },
            "put": {
                "summary": "Atualiza os dados de uma transa\u00e7\u00e3o especifica.",
                "description": "",
                "deprecated": false,
                "responses": {
                    "200": {
                        "description": "OK"
                    },
                    "401": {
                        "description": "(Unauthorized) Invalid or missing Access Token"
                    }
                },
                "tags": [
                    "Transa\u00e7\u00e3o"
                ],
                "parameters": [
                    {
                        "name": "transaction",
                        "in": "path",
                        "required": true,
                        "description": "",
                        "schema": {
                            "type": "string"
                        }
                    }
                ],
                "requestBody": {
                    "content": {
                        "application/json": {
                            "schema": {
                                "required": [
                                    "description"
                                ],
                                "properties": {
                                    "description": {
                                        "type": "string",
                                        "maxLength": 1000
                                    }
                                }
                            }
                        }
                    }
                },
                "security": [
                    {
                        "bearerAuth": []
                    }
                ]
            },
            "patch": {
                "summary": "Atualiza os dados de uma transa\u00e7\u00e3o especifica.",
                "description": "",
                "deprecated": false,
                "responses": {
                    "200": {
                        "description": "OK"
                    },
                    "401": {
                        "description": "(Unauthorized) Invalid or missing Access Token"
                    }
                },
                "tags": [
                    "Transa\u00e7\u00e3o"
                ],
                "parameters": [
                    {
                        "name": "transaction",
                        "in": "path",
                        "required": true,
                        "description": "",
                        "schema": {
                            "type": "string"
                        }
                    }
                ],
                "requestBody": {
                    "content": {
                        "application/json": {
                            "schema": {
                                "required": [
                                    "description"
                                ],
                                "properties": {
                                    "description": {
                                        "type": "string",
                                        "maxLength": 1000
                                    }
                                }
                            }
                        }
                    }
                },
                "security": [
                    {
                        "bearerAuth": []
                    }
                ]
            }
        },
        "/v1/accounts": {
            "get": {
                "summary": "Recupera uma lista paginada de contas do usu\u00e1rio.",
                "description": "",
                "deprecated": false,
                "responses": {
                    "200": {
                        "description": "OK"
                    },
                    "401": {
                        "description": "(Unauthorized) Invalid or missing Access Token"
                    }
                },
                "tags": [
                    "Conta"
                ],
                "security": [
                    {
                        "bearerAuth": []
                    }
                ]
            },
            "post": {
                "summary": "Cria uma nova conta.",
                "description": "",
                "deprecated": false,
                "responses": {
                    "200": {
                        "description": "OK"
                    },
                    "401": {
                        "description": "(Unauthorized) Invalid or missing Access Token"
                    }
                },
                "tags": [
                    "Conta"
                ],
                "requestBody": {
                    "content": {
                        "application/json": {
                            "schema": {
                                "properties": {
                                    "balance": {
                                        "type": "string",
                                        "minLength": 0
                                    },
                                    "credit_limit": {
                                        "type": "string",
                                        "minLength": 0
                                    }
                                }
                            }
                        }
                    }
                },
                "security": [
                    {
                        "bearerAuth": []
                    }
                ]
            }
        },
        "/v1/accounts/{account}": {
            "get": {
                "summary": "Recupera os dados de uma conta espec\u00edfica.",
                "description": "",
                "deprecated": false,
                "responses": {
                    "200": {
                        "description": "OK"
                    },
                    "401": {
                        "description": "(Unauthorized) Invalid or missing Access Token"
                    }
                },
                "tags": [
                    "Conta"
                ],
                "parameters": [
                    {
                        "name": "account",
                        "in": "path",
                        "required": true,
                        "description": "",
                        "schema": {
                            "type": "string"
                        }
                    }
                ],
                "security": [
                    {
                        "bearerAuth": []
                    }
                ]
            }
        },
        "/v1/fees": {
            "get": {
                "summary": "Recupera uma lista paginada de Taxas.",
                "description": "",
                "deprecated": false,
                "responses": {
                    "200": {
                        "description": "OK"
                    },
                    "401": {
                        "description": "(Unauthorized) Invalid or missing Access Token"
                    }
                },
                "tags": [
                    "Taxa"
                ],
                "security": [
                    {
                        "bearerAuth": []
                    }
                ]
            },
            "post": {
                "summary": "Cria uma nova Taxa.",
                "description": "",
                "deprecated": false,
                "responses": {
                    "200": {
                        "description": "OK"
                    },
                    "401": {
                        "description": "(Unauthorized) Invalid or missing Access Token"
                    }
                },
                "tags": [
                    "Taxa"
                ],
                "requestBody": {
                    "content": {
                        "application/json": {
                            "schema": {
                                "required": [
                                    "name",
                                    "type",
                                    "value",
                                    "transaction_type_name"
                                ],
                                "properties": {
                                    "name": {
                                        "type": "string",
                                        "maxLength": 255
                                    },
                                    "description": {
                                        "type": "string",
                                        "nullable": true,
                                        "maxLength": 1000
                                    },
                                    "type": {
                                        "type": "string",
                                        "enum": [
                                            "fixed",
                                            "percentage"
                                        ]
                                    },
                                    "value": {
                                        "type": "string",
                                        "minLength": 0
                                    },
                                    "transaction_type_name": {
                                        "type": "string"
                                    },
                                    "transaction_type_id": {
                                        "type": "string"
                                    }
                                }
                            }
                        }
                    }
                },
                "security": [
                    {
                        "bearerAuth": []
                    }
                ]
            }
        },
        "/v1/fees/{fee}": {
            "get": {
                "summary": "Recupera os dados de uma Taxa espec\u00edfica.",
                "description": "",
                "deprecated": false,
                "responses": {
                    "200": {
                        "description": "OK"
                    },
                    "401": {
                        "description": "(Unauthorized) Invalid or missing Access Token"
                    }
                },
                "tags": [
                    "Taxa"
                ],
                "parameters": [
                    {
                        "name": "fee",
                        "in": "path",
                        "required": true,
                        "description": "",
                        "schema": {
                            "type": "string"
                        }
                    }
                ],
                "security": [
                    {
                        "bearerAuth": []
                    }
                ]
            },
            "put": {
                "summary": "Atualiza os dados de uma Taxa espec\u00edfica.",
                "description": "",
                "deprecated": false,
                "responses": {
                    "200": {
                        "description": "OK"
                    },
                    "401": {
                        "description": "(Unauthorized) Invalid or missing Access Token"
                    }
                },
                "tags": [
                    "Taxa"
                ],
                "parameters": [
                    {
                        "name": "fee",
                        "in": "path",
                        "required": true,
                        "description": "",
                        "schema": {
                            "type": "string"
                        }
                    }
                ],
                "requestBody": {
                    "content": {
                        "application/json": {
                            "schema": {
                                "properties": {
                                    "name": {
                                        "type": "string",
                                        "maxLength": 255
                                    },
                                    "description": {
                                        "type": "string",
                                        "nullable": true,
                                        "maxLength": 1000
                                    },
                                    "type": {
                                        "type": "string",
                                        "enum": [
                                            "fixed",
                                            "percentage"
                                        ]
                                    },
                                    "value": {
                                        "type": "string",
                                        "minLength": 0
                                    },
                                    "transaction_type_name": {
                                        "type": "string"
                                    },
                                    "transaction_type_id": {
                                        "type": "string"
                                    }
                                }
                            }
                        }
                    }
                },
                "security": [
                    {
                        "bearerAuth": []
                    }
                ]
            },
            "patch": {
                "summary": "Atualiza os dados de uma Taxa espec\u00edfica.",
                "description": "",
                "deprecated": false,
                "responses": {
                    "200": {
                        "description": "OK"
                    },
                    "401": {
                        "description": "(Unauthorized) Invalid or missing Access Token"
                    }
                },
                "tags": [
                    "Taxa"
                ],
                "parameters": [
                    {
                        "name": "fee",
                        "in": "path",
                        "required": true,
                        "description": "",
                        "schema": {
                            "type": "string"
                        }
                    }
                ],
                "requestBody": {
                    "content": {
                        "application/json": {
                            "schema": {
                                "properties": {
                                    "name": {
                                        "type": "string",
                                        "maxLength": 255
                                    },
                                    "description": {
                                        "type": "string",
                                        "nullable": true,
                                        "maxLength": 1000
                                    },
                                    "type": {
                                        "type": "string",
                                        "enum": [
                                            "fixed",
                                            "percentage"
                                        ]
                                    },
                                    "value": {
                                        "type": "string",
                                        "minLength": 0
                                    },
                                    "transaction_type_name": {
                                        "type": "string"
                                    },
                                    "transaction_type_id": {
                                        "type": "string"
                                    }
                                }
                            }
                        }
                    }
                },
                "security": [
                    {
                        "bearerAuth": []
                    }
                ]
            },
            "delete": {
                "summary": "Remove uma Taxa espec\u00edfica.",
                "description": "",
                "deprecated": false,
                "responses": {
                    "200": {
                        "description": "OK"
                    },
                    "401": {
                        "description": "(Unauthorized) Invalid or missing Access Token"
                    }
                },
                "tags": [
                    "Taxa"
                ],
                "parameters": [
                    {
                        "name": "fee",
                        "in": "path",
                        "required": true,
                        "description": "",
                        "schema": {
                            "type": "string"
                        }
                    }
                ],
                "security": [
                    {
                        "bearerAuth": []
                    }
                ]
            }
        },
        "/v1/subledgers": {
            "get": {
                "summary": "Recupera uma lista paginada de Subledgers.",
                "description": "",
                "deprecated": false,
                "responses": {
                    "200": {
                        "description": "OK"
                    },
                    "401": {
                        "description": "(Unauthorized) Invalid or missing Access Token"
                    }
                },
                "tags": [
                    "Subledger"
                ],
                "security": [
                    {
                        "bearerAuth": []
                    }
                ]
            }
        },
        "/v1/subledgers/{subledger}": {
            "get": {
                "summary": "Recupera os dados de uma Subledger espec\u00edfico.",
                "description": "",
                "deprecated": false,
                "responses": {
                    "200": {
                        "description": "OK"
                    },
                    "401": {
                        "description": "(Unauthorized) Invalid or missing Access Token"
                    }
                },
                "tags": [
                    "Subledger"
                ],
                "parameters": [
                    {
                        "name": "subledger",
                        "in": "path",
                        "required": true,
                        "description": "",
                        "schema": {
                            "type": "string"
                        }
                    }
                ],
                "security": [
                    {
                        "bearerAuth": []
                    }
                ]
            },
            "put": {
                "summary": "Atualiza os dados de uma Subledger espec\u00edfico.",
                "description": "",
                "deprecated": false,
                "responses": {
                    "200": {
                        "description": "OK"
                    },
                    "401": {
                        "description": "(Unauthorized) Invalid or missing Access Token"
                    }
                },
                "tags": [
                    "Subledger"
                ],
                "parameters": [
                    {
                        "name": "subledger",
                        "in": "path",
                        "required": true,
                        "description": "",
                        "schema": {
                            "type": "string"
                        }
                    }
                ],
                "requestBody": {
                    "content": {
                        "application/json": {
                            "schema": {
                                "properties": {
                                    "name": {
                                        "type": "string",
                                        "nullable": true,
                                        "maxLength": 255
                                    },
                                    "description": {
                                        "type": "string",
                                        "nullable": true,
                                        "maxLength": 1000
                                    }
                                }
                            }
                        }
                    }
                },
                "security": [
                    {
                        "bearerAuth": []
                    }
                ]
            },
            "patch": {
                "summary": "Atualiza os dados de uma Subledger espec\u00edfico.",
                "description": "",
                "deprecated": false,
                "responses": {
                    "200": {
                        "description": "OK"
                    },
                    "401": {
                        "description": "(Unauthorized) Invalid or missing Access Token"
                    }
                },
                "tags": [
                    "Subledger"
                ],
                "parameters": [
                    {
                        "name": "subledger",
                        "in": "path",
                        "required": true,
                        "description": "",
                        "schema": {
                            "type": "string"
                        }
                    }
                ],
                "requestBody": {
                    "content": {
                        "application/json": {
                            "schema": {
                                "properties": {
                                    "name": {
                                        "type": "string",
                                        "nullable": true,
                                        "maxLength": 255
                                    },
                                    "description": {
                                        "type": "string",
                                        "nullable": true,
                                        "maxLength": 1000
                                    }
                                }
                            }
                        }
                    }
                },
                "security": [
                    {
                        "bearerAuth": []
                    }
                ]
            }
        },
        "/v1/trails": {
            "get": {
                "summary": "Recupera uma lista paginada de trails.",
                "description": "",
                "deprecated": false,
                "responses": {
                    "200": {
                        "description": "OK"
                    },
                    "401": {
                        "description": "(Unauthorized) Invalid or missing Access Token"
                    }
                },
                "tags": [
                    "Trail"
                ],
                "parameters": [
                    {
                        "in": "query",
                        "name": "action",
                        "description": "",
                        "required": false,
                        "enum": [
                            "created",
                            "updated",
                            "deleted"
                        ]
                    },
                    {
                        "in": "query",
                        "name": "relation_name",
                        "description": "",
                        "required": false,
                        "enum": [
                            "accounts",
                            "transactions"
                        ]
                    },
                    {
                        "in": "query",
                        "name": "relation_id",
                        "description": "",
                        "required": false,
                        "schema": {
                            "type": "integer"
                        }
                    }
                ],
                "security": [
                    {
                        "bearerAuth": []
                    }
                ]
            }
        },
        "/v1/trails/{trail}": {
            "get": {
                "summary": "Exibe uma trail em espec\u00edfica.",
                "description": "",
                "deprecated": false,
                "responses": {
                    "200": {
                        "description": "OK"
                    },
                    "401": {
                        "description": "(Unauthorized) Invalid or missing Access Token"
                    }
                },
                "tags": [
                    "Trail"
                ],
                "parameters": [
                    {
                        "name": "trail",
                        "in": "path",
                        "required": true,
                        "description": "",
                        "schema": {
                            "type": "string"
                        }
                    }
                ],
                "security": [
                    {
                        "bearerAuth": []
                    }
                ]
            }
        }
    },
    "tags": [],
    "components": {
        "schemas": {
            "Account": {
                "type": "object",
                "properties": {
                    "id": {
                        "name": "id",
                        "type_name": "int8",
                        "type": "bigint",
                        "collation": null,
                        "nullable": false,
                        "default": "nextval('accounts_id_seq'::regclass)",
                        "auto_increment": true,
                        "comment": null,
                        "generation": null,
                        "example": 7804812489262503514
                    },
                    "number": {
                        "name": "number",
                        "type_name": "int8",
                        "type": "bigint",
                        "collation": null,
                        "nullable": false,
                        "default": "nextval('accounts_number_seq'::regclass)",
                        "auto_increment": true,
                        "comment": null,
                        "generation": null,
                        "example": 3573783026162154277
                    },
                    "balance": {
                        "name": "balance",
                        "type_name": "int8",
                        "type": "bigint",
                        "collation": null,
                        "nullable": false,
                        "default": "'0'::bigint",
                        "auto_increment": false,
                        "comment": null,
                        "generation": null,
                        "example": 3753802649090288518
                    },
                    "credit_limit": {
                        "name": "credit_limit",
                        "type_name": "int8",
                        "type": "bigint",
                        "collation": null,
                        "nullable": false,
                        "default": "'0'::bigint",
                        "auto_increment": false,
                        "comment": null,
                        "generation": null,
                        "example": 4873629282399559625
                    },
                    "user_id": {
                        "name": "user_id",
                        "type_name": "int8",
                        "type": "bigint",
                        "collation": null,
                        "nullable": false,
                        "default": null,
                        "auto_increment": false,
                        "comment": null,
                        "generation": null,
                        "example": 2663848620920211613
                    },
                    "deleted_at": {
                        "name": "deleted_at",
                        "type_name": "timestamp",
                        "type": "timestamp(0) without time zone",
                        "collation": null,
                        "nullable": true,
                        "default": null,
                        "auto_increment": false,
                        "comment": null,
                        "generation": null
                    },
                    "created_at": {
                        "name": "created_at",
                        "type_name": "timestamp",
                        "type": "timestamp(0) without time zone",
                        "collation": null,
                        "nullable": true,
                        "default": null,
                        "auto_increment": false,
                        "comment": null,
                        "generation": null
                    },
                    "updated_at": {
                        "name": "updated_at",
                        "type_name": "timestamp",
                        "type": "timestamp(0) without time zone",
                        "collation": null,
                        "nullable": true,
                        "default": null,
                        "auto_increment": false,
                        "comment": null,
                        "generation": null
                    },
                    "user": {
                        "type": "object",
                        "$ref": "#/components/schemas/User"
                    },
                    "transactions": {
                        "type": "array",
                        "items": {
                            "type": "object",
                            "$ref": "#/components/schemas/Transaction"
                        }
                    },
                    "inflows": {
                        "type": "array",
                        "items": {
                            "type": "object",
                            "$ref": "#/components/schemas/Transaction"
                        }
                    },
                    "subledgers": {
                        "type": "array",
                        "items": {
                            "type": "object",
                            "$ref": "#/components/schemas/Subledger"
                        }
                    },
                    "trails": {
                        "type": "array",
                        "items": {
                            "type": "object",
                            "$ref": "#/components/schemas/Trail"
                        }
                    }
                },
                "required": [
                    "id",
                    "number",
                    "balance",
                    "credit_limit",
                    "user_id"
                ]
            },
            "Fee": {
                "type": "object",
                "properties": {
                    "id": {
                        "name": "id",
                        "type_name": "int8",
                        "type": "bigint",
                        "collation": null,
                        "nullable": false,
                        "default": "nextval('fees_id_seq'::regclass)",
                        "auto_increment": true,
                        "comment": null,
                        "generation": null,
                        "example": 1146579381539809232
                    },
                    "name": {
                        "name": "name",
                        "type_name": "varchar",
                        "type": "character varying(255)",
                        "collation": null,
                        "nullable": false,
                        "default": null,
                        "auto_increment": false,
                        "comment": null,
                        "generation": null
                    },
                    "description": {
                        "name": "description",
                        "type_name": "text",
                        "type": "text",
                        "collation": null,
                        "nullable": true,
                        "default": null,
                        "auto_increment": false,
                        "comment": null,
                        "generation": null,
                        "example": "a long text"
                    },
                    "type": {
                        "name": "type",
                        "type_name": "varchar",
                        "type": "character varying(255)",
                        "collation": null,
                        "nullable": false,
                        "default": null,
                        "auto_increment": false,
                        "comment": null,
                        "generation": null
                    },
                    "value": {
                        "name": "value",
                        "type_name": "int8",
                        "type": "bigint",
                        "collation": null,
                        "nullable": false,
                        "default": "'0'::bigint",
                        "auto_increment": false,
                        "comment": null,
                        "generation": null,
                        "example": 8866007773264978378
                    },
                    "transaction_type_id": {
                        "name": "transaction_type_id",
                        "type_name": "int8",
                        "type": "bigint",
                        "collation": null,
                        "nullable": false,
                        "default": null,
                        "auto_increment": false,
                        "comment": null,
                        "generation": null,
                        "example": 8909011228323765431
                    },
                    "created_at": {
                        "name": "created_at",
                        "type_name": "timestamp",
                        "type": "timestamp(0) without time zone",
                        "collation": null,
                        "nullable": true,
                        "default": null,
                        "auto_increment": false,
                        "comment": null,
                        "generation": null
                    },
                    "updated_at": {
                        "name": "updated_at",
                        "type_name": "timestamp",
                        "type": "timestamp(0) without time zone",
                        "collation": null,
                        "nullable": true,
                        "default": null,
                        "auto_increment": false,
                        "comment": null,
                        "generation": null
                    },
                    "transactionType": {
                        "type": "object",
                        "$ref": "#/components/schemas/TransactionType"
                    }
                },
                "required": [
                    "id",
                    "name",
                    "type",
                    "value",
                    "transaction_type_id"
                ]
            },
            "Ledger": {
                "type": "object",
                "properties": {
                    "id": {
                        "name": "id",
                        "type_name": "int8",
                        "type": "bigint",
                        "collation": null,
                        "nullable": false,
                        "default": "nextval('ledgers_id_seq'::regclass)",
                        "auto_increment": true,
                        "comment": null,
                        "generation": null,
                        "example": 7648064749042025245
                    },
                    "name": {
                        "name": "name",
                        "type_name": "varchar",
                        "type": "character varying(255)",
                        "collation": null,
                        "nullable": false,
                        "default": null,
                        "auto_increment": false,
                        "comment": null,
                        "generation": null
                    },
                    "description": {
                        "name": "description",
                        "type_name": "text",
                        "type": "text",
                        "collation": null,
                        "nullable": true,
                        "default": null,
                        "auto_increment": false,
                        "comment": null,
                        "generation": null,
                        "example": "a long text"
                    },
                    "created_at": {
                        "name": "created_at",
                        "type_name": "timestamp",
                        "type": "timestamp(0) without time zone",
                        "collation": null,
                        "nullable": true,
                        "default": null,
                        "auto_increment": false,
                        "comment": null,
                        "generation": null
                    },
                    "updated_at": {
                        "name": "updated_at",
                        "type_name": "timestamp",
                        "type": "timestamp(0) without time zone",
                        "collation": null,
                        "nullable": true,
                        "default": null,
                        "auto_increment": false,
                        "comment": null,
                        "generation": null
                    },
                    "subledgers": {
                        "type": "array",
                        "items": {
                            "type": "object",
                            "$ref": "#/components/schemas/Subledger"
                        }
                    }
                },
                "required": [
                    "id",
                    "name"
                ]
            },
            "Subledger": {
                "type": "object",
                "properties": {
                    "id": {
                        "name": "id",
                        "type_name": "int8",
                        "type": "bigint",
                        "collation": null,
                        "nullable": false,
                        "default": "nextval('subledgers_id_seq'::regclass)",
                        "auto_increment": true,
                        "comment": null,
                        "generation": null,
                        "example": 4931686654109297093
                    },
                    "name": {
                        "name": "name",
                        "type_name": "varchar",
                        "type": "character varying(255)",
                        "collation": null,
                        "nullable": true,
                        "default": null,
                        "auto_increment": false,
                        "comment": null,
                        "generation": null
                    },
                    "description": {
                        "name": "description",
                        "type_name": "text",
                        "type": "text",
                        "collation": null,
                        "nullable": true,
                        "default": null,
                        "auto_increment": false,
                        "comment": null,
                        "generation": null,
                        "example": "a long text"
                    },
                    "value": {
                        "name": "value",
                        "type_name": "int8",
                        "type": "bigint",
                        "collation": null,
                        "nullable": false,
                        "default": "'0'::bigint",
                        "auto_increment": false,
                        "comment": null,
                        "generation": null,
                        "example": 1327071594018545250
                    },
                    "fee": {
                        "name": "fee",
                        "type_name": "int8",
                        "type": "bigint",
                        "collation": null,
                        "nullable": false,
                        "default": "'0'::bigint",
                        "auto_increment": false,
                        "comment": null,
                        "generation": null,
                        "example": 5082052372825279065
                    },
                    "ledger_id": {
                        "name": "ledger_id",
                        "type_name": "int8",
                        "type": "bigint",
                        "collation": null,
                        "nullable": false,
                        "default": null,
                        "auto_increment": false,
                        "comment": null,
                        "generation": null,
                        "example": 9193048257258749517
                    },
                    "transaction_id": {
                        "name": "transaction_id",
                        "type_name": "int8",
                        "type": "bigint",
                        "collation": null,
                        "nullable": false,
                        "default": null,
                        "auto_increment": false,
                        "comment": null,
                        "generation": null,
                        "example": 1549905744521500383
                    },
                    "account_id": {
                        "name": "account_id",
                        "type_name": "int8",
                        "type": "bigint",
                        "collation": null,
                        "nullable": false,
                        "default": null,
                        "auto_increment": false,
                        "comment": null,
                        "generation": null,
                        "example": 1843912268883686166
                    },
                    "created_at": {
                        "name": "created_at",
                        "type_name": "timestamp",
                        "type": "timestamp(0) without time zone",
                        "collation": null,
                        "nullable": true,
                        "default": null,
                        "auto_increment": false,
                        "comment": null,
                        "generation": null
                    },
                    "updated_at": {
                        "name": "updated_at",
                        "type_name": "timestamp",
                        "type": "timestamp(0) without time zone",
                        "collation": null,
                        "nullable": true,
                        "default": null,
                        "auto_increment": false,
                        "comment": null,
                        "generation": null
                    },
                    "ledger": {
                        "type": "object",
                        "$ref": "#/components/schemas/Ledger"
                    },
                    "transaction": {
                        "type": "object",
                        "$ref": "#/components/schemas/Transaction"
                    },
                    "account": {
                        "type": "object",
                        "$ref": "#/components/schemas/Account"
                    }
                },
                "required": [
                    "id",
                    "value",
                    "fee",
                    "ledger_id",
                    "transaction_id",
                    "account_id"
                ]
            },
            "Trail": {
                "type": "object",
                "properties": {
                    "id": {
                        "name": "id",
                        "type_name": "int8",
                        "type": "bigint",
                        "collation": null,
                        "nullable": false,
                        "default": "nextval('trails_id_seq'::regclass)",
                        "auto_increment": true,
                        "comment": null,
                        "generation": null,
                        "example": 8499509062101955403
                    },
                    "action": {
                        "name": "action",
                        "type_name": "varchar",
                        "type": "character varying(255)",
                        "collation": null,
                        "nullable": false,
                        "default": null,
                        "auto_increment": false,
                        "comment": null,
                        "generation": null
                    },
                    "trailable_type": {
                        "name": "trailable_type",
                        "type_name": "varchar",
                        "type": "character varying(255)",
                        "collation": null,
                        "nullable": false,
                        "default": null,
                        "auto_increment": false,
                        "comment": null,
                        "generation": null
                    },
                    "trailable_id": {
                        "name": "trailable_id",
                        "type_name": "int8",
                        "type": "bigint",
                        "collation": null,
                        "nullable": false,
                        "default": null,
                        "auto_increment": false,
                        "comment": null,
                        "generation": null,
                        "example": 2893137774772685923
                    },
                    "before": {
                        "name": "before",
                        "type_name": "json",
                        "type": "json",
                        "collation": null,
                        "nullable": true,
                        "default": null,
                        "auto_increment": false,
                        "comment": null,
                        "generation": null
                    },
                    "after": {
                        "name": "after",
                        "type_name": "json",
                        "type": "json",
                        "collation": null,
                        "nullable": true,
                        "default": null,
                        "auto_increment": false,
                        "comment": null,
                        "generation": null
                    },
                    "user_id": {
                        "name": "user_id",
                        "type_name": "int8",
                        "type": "bigint",
                        "collation": null,
                        "nullable": true,
                        "default": null,
                        "auto_increment": false,
                        "comment": null,
                        "generation": null,
                        "example": 2930674527490675519
                    },
                    "created_at": {
                        "name": "created_at",
                        "type_name": "timestamp",
                        "type": "timestamp(0) without time zone",
                        "collation": null,
                        "nullable": true,
                        "default": null,
                        "auto_increment": false,
                        "comment": null,
                        "generation": null
                    },
                    "updated_at": {
                        "name": "updated_at",
                        "type_name": "timestamp",
                        "type": "timestamp(0) without time zone",
                        "collation": null,
                        "nullable": true,
                        "default": null,
                        "auto_increment": false,
                        "comment": null,
                        "generation": null
                    },
                    "trailable": {
                        "type": "object",
                        "$ref": "#/components/schemas/Trail"
                    }
                },
                "required": [
                    "id",
                    "action",
                    "trailable_type",
                    "trailable_id"
                ]
            },
            "Transaction": {
                "type": "object",
                "properties": {
                    "id": {
                        "name": "id",
                        "type_name": "int8",
                        "type": "bigint",
                        "collation": null,
                        "nullable": false,
                        "default": "nextval('transactions_id_seq'::regclass)",
                        "auto_increment": true,
                        "comment": null,
                        "generation": null,
                        "example": 2580888478578880285
                    },
                    "description": {
                        "name": "description",
                        "type_name": "text",
                        "type": "text",
                        "collation": null,
                        "nullable": true,
                        "default": null,
                        "auto_increment": false,
                        "comment": null,
                        "generation": null,
                        "example": "a long text"
                    },
                    "type": {
                        "name": "type",
                        "type_name": "varchar",
                        "type": "character varying(255)",
                        "collation": null,
                        "nullable": false,
                        "default": null,
                        "auto_increment": false,
                        "comment": null,
                        "generation": null
                    },
                    "status": {
                        "name": "status",
                        "type_name": "varchar",
                        "type": "character varying(255)",
                        "collation": null,
                        "nullable": false,
                        "default": null,
                        "auto_increment": false,
                        "comment": null,
                        "generation": null
                    },
                    "message": {
                        "name": "message",
                        "type_name": "text",
                        "type": "text",
                        "collation": null,
                        "nullable": true,
                        "default": null,
                        "auto_increment": false,
                        "comment": null,
                        "generation": null,
                        "example": "a long text"
                    },
                    "amount": {
                        "name": "amount",
                        "type_name": "int8",
                        "type": "bigint",
                        "collation": null,
                        "nullable": false,
                        "default": "'0'::bigint",
                        "auto_increment": false,
                        "comment": null,
                        "generation": null,
                        "example": 1707589234152206924
                    },
                    "fee": {
                        "name": "fee",
                        "type_name": "int8",
                        "type": "bigint",
                        "collation": null,
                        "nullable": false,
                        "default": "'0'::bigint",
                        "auto_increment": false,
                        "comment": null,
                        "generation": null,
                        "example": 2519270271345203068
                    },
                    "total": {
                        "name": "total",
                        "type_name": "int8",
                        "type": "bigint",
                        "collation": null,
                        "nullable": false,
                        "default": "'0'::bigint",
                        "auto_increment": false,
                        "comment": null,
                        "generation": null,
                        "example": 3838293123983492826
                    },
                    "transaction_type_id": {
                        "name": "transaction_type_id",
                        "type_name": "int8",
                        "type": "bigint",
                        "collation": null,
                        "nullable": false,
                        "default": null,
                        "auto_increment": false,
                        "comment": null,
                        "generation": null,
                        "example": 5277370541158452834
                    },
                    "account_id": {
                        "name": "account_id",
                        "type_name": "int8",
                        "type": "bigint",
                        "collation": null,
                        "nullable": true,
                        "default": null,
                        "auto_increment": false,
                        "comment": null,
                        "generation": null,
                        "example": 3861982035324888379
                    },
                    "payee_id": {
                        "name": "payee_id",
                        "type_name": "int8",
                        "type": "bigint",
                        "collation": null,
                        "nullable": true,
                        "default": null,
                        "auto_increment": false,
                        "comment": null,
                        "generation": null,
                        "example": 3492141898236111116
                    },
                    "created_at": {
                        "name": "created_at",
                        "type_name": "timestamp",
                        "type": "timestamp(0) without time zone",
                        "collation": null,
                        "nullable": true,
                        "default": null,
                        "auto_increment": false,
                        "comment": null,
                        "generation": null
                    },
                    "updated_at": {
                        "name": "updated_at",
                        "type_name": "timestamp",
                        "type": "timestamp(0) without time zone",
                        "collation": null,
                        "nullable": true,
                        "default": null,
                        "auto_increment": false,
                        "comment": null,
                        "generation": null
                    },
                    "transactionType": {
                        "type": "object",
                        "$ref": "#/components/schemas/TransactionType"
                    },
                    "account": {
                        "type": "object",
                        "$ref": "#/components/schemas/Account"
                    },
                    "payee": {
                        "type": "object",
                        "$ref": "#/components/schemas/Account"
                    },
                    "subledgers": {
                        "type": "array",
                        "items": {
                            "type": "object",
                            "$ref": "#/components/schemas/Subledger"
                        }
                    },
                    "trails": {
                        "type": "array",
                        "items": {
                            "type": "object",
                            "$ref": "#/components/schemas/Trail"
                        }
                    }
                },
                "required": [
                    "id",
                    "type",
                    "status",
                    "amount",
                    "fee",
                    "total",
                    "transaction_type_id"
                ]
            },
            "TransactionType": {
                "type": "object",
                "properties": {
                    "id": {
                        "name": "id",
                        "type_name": "int8",
                        "type": "bigint",
                        "collation": null,
                        "nullable": false,
                        "default": "nextval('transaction_types_id_seq'::regclass)",
                        "auto_increment": true,
                        "comment": null,
                        "generation": null,
                        "example": 2284066304369112616
                    },
                    "name": {
                        "name": "name",
                        "type_name": "varchar",
                        "type": "character varying(255)",
                        "collation": null,
                        "nullable": false,
                        "default": null,
                        "auto_increment": false,
                        "comment": null,
                        "generation": null
                    },
                    "slug": {
                        "name": "slug",
                        "type_name": "varchar",
                        "type": "character varying(255)",
                        "collation": null,
                        "nullable": false,
                        "default": null,
                        "auto_increment": false,
                        "comment": null,
                        "generation": null
                    },
                    "description": {
                        "name": "description",
                        "type_name": "text",
                        "type": "text",
                        "collation": null,
                        "nullable": true,
                        "default": null,
                        "auto_increment": false,
                        "comment": null,
                        "generation": null,
                        "example": "a long text"
                    },
                    "created_at": {
                        "name": "created_at",
                        "type_name": "timestamp",
                        "type": "timestamp(0) without time zone",
                        "collation": null,
                        "nullable": true,
                        "default": null,
                        "auto_increment": false,
                        "comment": null,
                        "generation": null
                    },
                    "updated_at": {
                        "name": "updated_at",
                        "type_name": "timestamp",
                        "type": "timestamp(0) without time zone",
                        "collation": null,
                        "nullable": true,
                        "default": null,
                        "auto_increment": false,
                        "comment": null,
                        "generation": null
                    },
                    "transactions": {
                        "type": "array",
                        "items": {
                            "type": "object",
                            "$ref": "#/components/schemas/Transaction"
                        }
                    },
                    "fees": {
                        "type": "array",
                        "items": {
                            "type": "object",
                            "$ref": "#/components/schemas/Fee"
                        }
                    }
                },
                "required": [
                    "id",
                    "name",
                    "slug"
                ]
            },
            "User": {
                "type": "object",
                "properties": {
                    "id": {
                        "name": "id",
                        "type_name": "int8",
                        "type": "bigint",
                        "collation": null,
                        "nullable": false,
                        "default": "nextval('users_id_seq'::regclass)",
                        "auto_increment": true,
                        "comment": null,
                        "generation": null,
                        "example": 1681050145276589711
                    },
                    "name": {
                        "name": "name",
                        "type_name": "varchar",
                        "type": "character varying(255)",
                        "collation": null,
                        "nullable": false,
                        "default": null,
                        "auto_increment": false,
                        "comment": null,
                        "generation": null
                    },
                    "email": {
                        "name": "email",
                        "type_name": "varchar",
                        "type": "character varying(255)",
                        "collation": null,
                        "nullable": false,
                        "default": null,
                        "auto_increment": false,
                        "comment": null,
                        "generation": null
                    },
                    "email_verified_at": {
                        "name": "email_verified_at",
                        "type_name": "timestamp",
                        "type": "timestamp(0) without time zone",
                        "collation": null,
                        "nullable": true,
                        "default": null,
                        "auto_increment": false,
                        "comment": null,
                        "generation": null
                    },
                    "password": {
                        "name": "password",
                        "type_name": "varchar",
                        "type": "character varying(255)",
                        "collation": null,
                        "nullable": false,
                        "default": null,
                        "auto_increment": false,
                        "comment": null,
                        "generation": null
                    },
                    "remember_token": {
                        "name": "remember_token",
                        "type_name": "varchar",
                        "type": "character varying(100)",
                        "collation": null,
                        "nullable": true,
                        "default": null,
                        "auto_increment": false,
                        "comment": null,
                        "generation": null
                    },
                    "current_team_id": {
                        "name": "current_team_id",
                        "type_name": "int8",
                        "type": "bigint",
                        "collation": null,
                        "nullable": true,
                        "default": null,
                        "auto_increment": false,
                        "comment": null,
                        "generation": null,
                        "example": 7556246238360383553
                    },
                    "profile_photo_path": {
                        "name": "profile_photo_path",
                        "type_name": "varchar",
                        "type": "character varying(2048)",
                        "collation": null,
                        "nullable": true,
                        "default": null,
                        "auto_increment": false,
                        "comment": null,
                        "generation": null
                    },
                    "deleted_at": {
                        "name": "deleted_at",
                        "type_name": "timestamp",
                        "type": "timestamp(0) without time zone",
                        "collation": null,
                        "nullable": true,
                        "default": null,
                        "auto_increment": false,
                        "comment": null,
                        "generation": null
                    },
                    "created_at": {
                        "name": "created_at",
                        "type_name": "timestamp",
                        "type": "timestamp(0) without time zone",
                        "collation": null,
                        "nullable": true,
                        "default": null,
                        "auto_increment": false,
                        "comment": null,
                        "generation": null
                    },
                    "updated_at": {
                        "name": "updated_at",
                        "type_name": "timestamp",
                        "type": "timestamp(0) without time zone",
                        "collation": null,
                        "nullable": true,
                        "default": null,
                        "auto_increment": false,
                        "comment": null,
                        "generation": null
                    },
                    "two_factor_secret": {
                        "name": "two_factor_secret",
                        "type_name": "text",
                        "type": "text",
                        "collation": null,
                        "nullable": true,
                        "default": null,
                        "auto_increment": false,
                        "comment": null,
                        "generation": null,
                        "example": "a long text"
                    },
                    "two_factor_recovery_codes": {
                        "name": "two_factor_recovery_codes",
                        "type_name": "text",
                        "type": "text",
                        "collation": null,
                        "nullable": true,
                        "default": null,
                        "auto_increment": false,
                        "comment": null,
                        "generation": null,
                        "example": "a long text"
                    },
                    "accounts": {
                        "type": "array",
                        "items": {
                            "type": "object",
                            "$ref": "#/components/schemas/Account"
                        }
                    }
                },
                "required": [
                    "id",
                    "name",
                    "email",
                    "password"
                ]
            }
        },
        "securitySchemes": {
            "bearerAuth": {
                "type": "http",
                "scheme": "bearer",
                "bearerFormat": "JWT"
            }
        }
    }
}